logbot-0.2.0.dist-info/top_level.txt
logbot-0.2.0.dist-info/entry_points.txt
logbot-0.2.0.dist-info/METADATA
logbot-0.2.0.dist-info/RECORD
logbot-0.2.0.dist-info/DESCRIPTION.rst
logbot-0.2.0.dist-info/pydist.json
logbot-0.2.0.dist-info/WHEEL
logbot/__main__.py
logbot/__init__.py
logbot/log.py
logbot/bot.py
logbot/common.py
logbot/search.py
logbot/httpd/__init__.py
logbot/httpd/static/search.html
logbot/httpd/static/base.html
logbot/httpd/static/style.css
logbot/httpd/static/index.html
logbot/httpd/static/favicon.ico
logbot-0.2.0.data/scripts/logbot
