Metadata-Version: 2.0
Name: logbot
Version: 0.2.0
Summary: UNKNOWN
Home-page: UNKNOWN
Author: UNKNOWN
Author-email: UNKNOWN
License: UNKNOWN
Platform: UNKNOWN
Requires-Dist: flask
Requires-Dist: pytz
Requires-Dist: sleekxmpp
Requires-Dist: whoosh
